PColorLogging/__init__.py
PColorLogging/error.py
PColorLogging/Drawer/__init__.py
PColorLogging/Drawer/message_manager.py
PColorLogging/Drawer/utils.py
PColorLogging/Drawer/color/__init__.py
PColorLogging/Drawer/color/color_code.py
PColorLogging/Drawer/terminal/__init__.py
PColorLogging/Drawer/terminal/command_line_code.py
PColorLogging/Formatter/__init__.py
PColorLogging/Formatter/colored_formatter.py
PColorLogging/LogRecord/__init__.py
PColorLogging/Logger/__init__.py
PColorLogging/Logger/Adapter/__init__.py
PColorLogging/Logger/Adapter/extra_adapter_logger.py
PColorLogging/Utils/__init__.py
PColorLogging/Utils/process_console.py
PColorLogging-0.0.34.dist-info/LICENSE
PColorLogging-0.0.34.dist-info/METADATA
PColorLogging-0.0.34.dist-info/WHEEL
PColorLogging-0.0.34.dist-info/top_level.txt
PColorLogging-0.0.34.dist-info/RECORD
