Metadata-Version: 2.1
Name: PColorLogging
Version: 0.0.34
Summary: This is powerful logging
Home-page: https://github.com/phamhongphuc1999/PColorLogging
Author: Phạm Hồng Phúc
Author-email: phamhongphuc12atm1@gmail.com
Project-URL: Bug Tracker, https://github.com/phamhongphuc1999/PColorLogging
Classifier: Programming Language :: Python :: 3
Classifier: License :: OSI Approved :: MIT License
Classifier: Operating System :: OS Independent
Classifier: Environment :: Console
Requires-Python: >=3.6
License-File: LICENSE
